{
	"ServiceRoot": {
		"AccountService": true,
		"Links": {
			"Sessions": true
		},
		"Managers": true,
		"Tasks": true,
		"SessionService": true,
		"EventService": true,
		"Registries": true,
		"StorageSystems": true,
		"StorageServices": true,
		"Fabrics": true,
		"UpdateService": true
	},
	"Baseboard": {
		"Actions": {
			"#Baseboard.Reset": {
				"ResetType": [
					"On",
					"ForceOff",
					"GracefulShutdown",
					"GracefulRestart",
					"ForceRestart",
					"ForceOn",
					"PushPowerButton"
				]
			}
		}
	},
	"Chassis": {
		"AssetTag": true,
		"ChassisType": [
			"Enclosure"
		],
		"Links": {
			"ManagedBy": true,
			"PoweredBy": true,
			"CooledBy": true,
			"ContainedBy": true,
			"Contains": true,
			"ManagersInChassis": true,
			"Drives": true,
			"Storage": true
		},
		"Actions": {
			"#Chassis.Reset": true
		},
		"LogServices": true,
		"Thermal": true,
		"Power": true,
		"PhysicalSecurity": true,
		"Location": true,
		"HeightMm": true,
		"WidthMm": true,
		"DepthMm": true,
		"WeightKg": true,
		"NetworkAdapters": true
	},
	"ComposedNode": {
		"Actions": {
			"#ComposedNode.Reset": {
				"ResetType": [
					"On",
					"ForceOff",
					"GracefulShutdown",
					"GracefulRestart",
					"ForceRestart",
					"ForceOn",
					"PushPowerButton"
				]
			}
		}
	},
	"ComputerSystem": {
		"Boot": {
			"BootSourceOverrideTarget": [
				"None",
				"Pxe",
				"Cd",
				"Usb",
				"Hdd"
			]
		},
		"Links": {
			"ManagedBy": true,
			"PoweredBy": true,
			"CooledBy": true,
			"Endpoints": true
		},
		"Actions": {
			"#ComputerSystem.Reset": {
				"ResetType": [
					"On",
					"ForceOff",
					"GracefulShutdown",
					"GracefulRestart",
					"ForceRestart",
					"ForceOn",
					"PushPowerButton"
				]
			}
		},
		"AssetTag": true,
		"HostName": true,
		"MemorySummary": true,
		"MemoryMirroring": true,
		"SimpleStorage": true,
		"Memory": true,
		"LogServices": true,
		"TrustedModules": true,
		"SecureBoot": true,
		"Bios": true,
		"Storage": true,
		"HostingRoles": true,
		"HostedServices": true,
		"MemoryDomains": true,
		"NetworkInterfaces": true
	},
	"Drive": {
		"Links": {
			"Volumes": true,
			"Endpoints": true
		},
		"Operations": true
	},
	"EthernetInterface": {
		"Links": {
			"Endpoints": true,
			"HostInterface": true
		}
	},
	"EthernetSwitch": {
		"Links": {
			"ManagedBy": true
		}
	},
	"EthernetSwitchPort": {
		"Links": {
			"MemberOfPort": true,
			"PortMembers": true
		}
	},
	"Manager": {
		"LogServices": true,
		"HostInterfaces": true,
		"SerialInterfaces": true,
		"VirtualMedia": true
	},
	"Memory": {
		"FunctionClasses": true,
		"MaxTDPMilliWatts": true,
		"SecurityCapabilities": true,
		"SpareDeviceCount": true,
		"DeviceLocator": true,
		"VolatileRegionSizeLimitMiB": true,
		"PersistentRegionSizeLimitMiB": true,
		"Regions": true,
		"OperatingMemoryModes": true,
		"PowerManagementPolicy": true,
		"IsSpareDeviceEnabled": true,
		"IsRankSpareEnabled": true,
		"Actions": {
			"#Memory.DisablePassphrase": true,
			"#Memory.SecureEraseUnit": true,
			"#Memory.SetPassphrase": true,
			"#Memory.UnlockUnit": true
		},
		"Metrics": true
	},
	"PCIeDevice": {
		"AssetTag": true,
		"Links": {
			"Endpoints": true,
			"HostInterface": true
		}
	},
	"PCIeFunction": {
		"AssetTag": true,
		"Links": {
			"Endpoints": true,
			"Drives": true,
			"StorageControllers": true
		}
	},
	"PCIeSwitch": {
		"Links": {
			"ManagedBy": true,
			"PoweredBy": true,
			"CooledBy": true
		},
		"Actions": {
			"#PCIeSwitch.Reset": {
				"ResetType": [
					"On",
					"ForceOff",
					"GracefulShutdown",
					"GracefulRestart",
					"ForceRestart",
					"ForceOn",
					"PushPowerButton"
				]
			}
		},
		"LogServices": true
	}
}