{
    "$ref": "#/definitions/ComposedNodeCollection",
    "$schema": "http://redfish.dmtf.org/schemas/v1/redfish-schema.v1_3_0.json",
    "copyright": "Copyright 2014-2017 Distributed Management Task Force, Inc. (DMTF). For the full DMTF copyright policy, see http://www.dmtf.org/about/policies/copyright",
    "definitions": {
        "Actions": {
            "additionalProperties": false,
            "patternProperties": {
                "^([a-zA-Z_][a-zA-Z0-9_]*)?@(odata|Redfish|Message|Privileges)\\.[a-zA-Z_][a-zA-Z0-9_.]+$": {
                    "description": "This property shall specify a valid odata or Redfish property.",
                    "type": [
                        "array",
                        "boolean",
                        "number",
                        "null",
                        "object",
                        "string"
                    ]
                }
            },
            "properties": {
                "#ComposedNodeCollection.Allocate": {
                    "$ref": "#/definitions/Allocate"
                },
                "Oem": {
                    "$ref": "#/definitions/OemActions"
                }
            },
            "type": "object"
        },
        "Allocate": {
            "additionalProperties": false,
            "description": "This action is used to allocate a composed node.",
            "parameters": {
                "ComposedNodes": {
                    "items": {
                        "$ref": "ComposedNodeAllocationRequirement_v1.xml/ComposedNodeAllocationRequirement.v1_0_0.json#/definitions/ComposedNode"
                    },
                    "type": "array"
                },
                "Description": {
                    "description": "The description of the ComposedNode",
                    "type": "string"
                },
                "Devices": {
                    "items": {
                        "$ref": "ComposedNodeAllocationRequirement_v1.xml/ComposedNodeAllocationRequirement.v1_0_0.json#/definitions/Device"
                    },
                    "type": "array"
                },
                "Name": {
                    "description": "The name of the ComposedNode",
                    "type": "string"
                },
                "Ports": {
                    "items": {
                        "$ref": "ComposedNodeAllocationRequirement_v1.xml/ComposedNodeAllocationRequirement.v1_0_0.json#/definitions/Port"
                    },
                    "type": "array"
                },
                "Systems": {
                    "items": {
                        "$ref": "ComposedNodeAllocationRequirement_v1.xml/ComposedNodeAllocationRequirement.v1_0_0.json#/definitions/System"
                    },
                    "type": "array"
                }
            },
            "patternProperties": {
                "^([a-zA-Z_][a-zA-Z0-9_]*)?@(odata|Redfish|Message|Privileges)\\.[a-zA-Z_][a-zA-Z0-9_.]+$": {
                    "description": "This property shall specify a valid odata or Redfish property.",
                    "type": [
                        "array",
                        "boolean",
                        "number",
                        "null",
                        "object",
                        "string"
                    ]
                }
            },
            "properties": {
                "target": {
                    "description": "Link to invoke action",
                    "format": "uri",
                    "type": "string"
                },
                "title": {
                    "description": "Friendly action name",
                    "type": "string"
                }
            },
            "type": "object"
        },
        "ComposedNodeCollection": {
            "anyOf": [
                {
                    "$ref": "http://redfish.dmtf.org/schemas/v1/odata.v4_0_1.json#/definitions/idRef"
                },
                {
                    "additionalProperties": false,
                    "patternProperties": {
                        "^([a-zA-Z_][a-zA-Z0-9_]*)?@(odata|Redfish|Message|Privileges)\\.[a-zA-Z_][a-zA-Z0-9_.]+$": {
                            "description": "This property shall specify a valid odata or Redfish property.",
                            "type": [
                                "array",
                                "boolean",
                                "number",
                                "null",
                                "object",
                                "string"
                            ]
                        }
                    },
                    "properties": {
                        "@odata.context": {
                            "$ref": "http://redfish.dmtf.org/schemas/v1/odata.v4_0_1.json#/definitions/context"
                        },
                        "@odata.id": {
                            "$ref": "http://redfish.dmtf.org/schemas/v1/odata.v4_0_1.json#/definitions/id"
                        },
                        "@odata.type": {
                            "$ref": "http://redfish.dmtf.org/schemas/v1/odata.v4_0_1.json#/definitions/type"
                        },
                        "Actions": {
                            "$ref": "#/definitions/Actions",
                            "description": "The available actions for this resource.",
                            "longDescription": "The Actions property shall contain the available actions for this resource."
                        },
                        "Description": {
                            "anyOf": [
                                {
                                    "$ref": "http://redfish.dmtf.org/schemas/v1/Resource.json#/definitions/Description"
                                },
                                {
                                    "type": "null"
                                }
                            ],
                            "readonly": true
                        },
                        "Members": {
                            "description": "Contains the members of this collection.",
                            "items": {
                                "$ref": "ComposedNode_v1.xml/ComposedNode.json#/definitions/ComposedNode"
                            },
                            "readonly": true,
                            "type": "array"
                        },
                        "Members@odata.count": {
                            "$ref": "http://redfish.dmtf.org/schemas/v1/odata.v4_0_1.json#/definitions/count"
                        },
                        "Name": {
                            "$ref": "http://redfish.dmtf.org/schemas/v1/Resource.json#/definitions/Name",
                            "readonly": true
                        },
                        "Oem": {
                            "$ref": "http://redfish.dmtf.org/schemas/v1/Resource.json#/definitions/Oem",
                            "description": "This is the manufacturer/provider specific extension moniker used to divide the Oem object into sections.",
                            "longDescription": "The value of this string shall be of the format for the reserved word *Oem*."
                        }
                    },
                    "type": "object"
                }
            ]
        },
        "OemActions": {
            "additionalProperties": true,
            "patternProperties": {
                "^([a-zA-Z_][a-zA-Z0-9_]*)?@(odata|Redfish|Message|Privileges)\\.[a-zA-Z_][a-zA-Z0-9_.]+$": {
                    "description": "This property shall specify a valid odata or Redfish property.",
                    "type": [
                        "array",
                        "boolean",
                        "number",
                        "null",
                        "object",
                        "string"
                    ]
                }
            },
            "properties": {},
            "type": "object"
        }
    },
    "title": "#ComposedNodeCollection.ComposedNodeCollection"
}